lumenova_beacon/__init__.py
lumenova_beacon/exceptions.py
lumenova_beacon/types.py
lumenova_beacon/core/__init__.py
lumenova_beacon/core/client.py
lumenova_beacon/core/config.py
lumenova_beacon/core/transport.py
lumenova_beacon/datasets/__init__.py
lumenova_beacon/datasets/models.py
lumenova_beacon/datasets/types.py
lumenova_beacon/evaluations/__init__.py
lumenova_beacon/evaluations/models.py
lumenova_beacon/evaluations/types.py
lumenova_beacon/experiments/__init__.py
lumenova_beacon/experiments/models.py
lumenova_beacon/experiments/types.py
lumenova_beacon/llm_configs/__init__.py
lumenova_beacon/llm_configs/models.py
lumenova_beacon/llm_configs/types.py
lumenova_beacon/masking/__init__.py
lumenova_beacon/masking/engine.py
lumenova_beacon/masking/types.py
lumenova_beacon/masking/utils.py
lumenova_beacon/masking/integrations/__init__.py
lumenova_beacon/masking/integrations/beacon_guardrails.py
lumenova_beacon/prompts/__init__.py
lumenova_beacon/prompts/models.py
lumenova_beacon/prompts/rendering.py
lumenova_beacon/prompts/types.py
lumenova_beacon/providers/__init__.py
lumenova_beacon/tracing/__init__.py
lumenova_beacon/tracing/decorators.py
lumenova_beacon/tracing/span.py
lumenova_beacon/tracing/trace.py
lumenova_beacon/tracing/exporters/__init__.py
lumenova_beacon/tracing/exporters/opentelemetry.py
lumenova_beacon/tracing/integrations/__init__.py
lumenova_beacon/tracing/integrations/langchain.py
lumenova_beacon/tracing/integrations/litellm.py
lumenova_beacon/utils/__init__.py
lumenova_beacon/utils/client_helpers.py
lumenova_beacon/utils/config.py
lumenova_beacon/utils/datetime.py
lumenova_beacon/utils/http_errors.py
lumenova_beacon/utils/ids.py
lumenova_beacon/utils/serialization.py
lumenova_beacon/utils/spans.py
lumenova_beacon/utils/timestamps.py
lumenova_beacon-2.2.3.dist-info/METADATA
lumenova_beacon-2.2.3.dist-info/WHEEL
lumenova_beacon-2.2.3.dist-info/licenses/LICENSE
lumenova_beacon-2.2.3.dist-info/RECORD
