Metadata-Version: 2.4
Name: lumenova-beacon
Version: 2.2.3
Summary: Lumenova Beacon SDK - A Python SDK for observability tracing with OpenTelemetry-compatible span export
Project-URL: Homepage, https://lumenova.ai
Author-email: Lumenova AI <support@lumenova.ai>
Maintainer-email: Lumenova AI <support@lumenova.ai>
License-Expression: Apache-2.0
License-File: LICENSE
Keywords: ai,langchain,llm,monitoring,observability,opentelemetry,sdk,tracing
Classifier: Development Status :: 4 - Beta
Classifier: Intended Audience :: Developers
Classifier: License :: OSI Approved :: Apache Software License
Classifier: Operating System :: OS Independent
Classifier: Programming Language :: Python :: 3
Classifier: Programming Language :: Python :: 3.10
Classifier: Programming Language :: Python :: 3.11
Classifier: Programming Language :: Python :: 3.12
Classifier: Programming Language :: Python :: 3.13
Classifier: Topic :: Software Development :: Libraries :: Python Modules
Classifier: Topic :: System :: Monitoring
Classifier: Typing :: Typed
Requires-Python: >=3.10
Requires-Dist: httpx>=0.27.0
Requires-Dist: tenacity>=9.0.0
Requires-Dist: typing-extensions>=4.12.0
Provides-Extra: crewai
Requires-Dist: crewai>=0.28.0; extra == 'crewai'
Requires-Dist: openinference-instrumentation-crewai>=0.1.0; extra == 'crewai'
Requires-Dist: openinference-instrumentation-litellm>=0.1.0; extra == 'crewai'
Provides-Extra: dev
Requires-Dist: black>=24.0.0; extra == 'dev'
Requires-Dist: ipython>=8.37.0; extra == 'dev'
Requires-Dist: mypy>=1.10.0; extra == 'dev'
Requires-Dist: pytest-asyncio>=0.23.0; extra == 'dev'
Requires-Dist: pytest>=8.0.0; extra == 'dev'
Requires-Dist: ruff>=0.4.0; extra == 'dev'
Provides-Extra: examples
Requires-Dist: anthropic>=0.40.0; extra == 'examples'
Requires-Dist: crewai>=0.1.0; extra == 'examples'
Requires-Dist: fastapi>=0.115.0; extra == 'examples'
Requires-Dist: google-genai>=1.0.0; extra == 'examples'
Requires-Dist: litellm>=1.70.0; extra == 'examples'
Requires-Dist: llama-index-core>=0.12.3; extra == 'examples'
Requires-Dist: llama-index-embeddings-azure-openai>=0.3.0; extra == 'examples'
Requires-Dist: llama-index-llms-azure-openai>=0.3.0; extra == 'examples'
Requires-Dist: openai>=1.0.0; extra == 'examples'
Requires-Dist: openinference-instrumentation-crewai>=0.1.0; extra == 'examples'
Requires-Dist: openinference-instrumentation-google-genai>=0.1.0; extra == 'examples'
Requires-Dist: openinference-instrumentation-litellm>=0.1.0; extra == 'examples'
Requires-Dist: openinference-instrumentation-llama-index>=4.3.8; extra == 'examples'
Requires-Dist: opentelemetry-instrumentation-anthropic>=0.1.0; extra == 'examples'
Requires-Dist: opentelemetry-instrumentation-fastapi==0.59b0; extra == 'examples'
Requires-Dist: opentelemetry-instrumentation-httpx==0.59b0; extra == 'examples'
Requires-Dist: opentelemetry-instrumentation-openai>=0.1.0; extra == 'examples'
Requires-Dist: opentelemetry-instrumentation-redis==0.59b0; extra == 'examples'
Requires-Dist: opentelemetry-instrumentation-requests==0.59b0; extra == 'examples'
Requires-Dist: opentelemetry-instrumentation==0.59b0; extra == 'examples'
Requires-Dist: python-dotenv>=1.0.0; extra == 'examples'
Requires-Dist: redis>=5.0.0; extra == 'examples'
Requires-Dist: requests>=2.31.0; extra == 'examples'
Requires-Dist: strands-agents-tools>=0.2.0; extra == 'examples'
Requires-Dist: strands-agents>=1.15.0; extra == 'examples'
Provides-Extra: langchain
Requires-Dist: faiss-cpu>=1.13.1; extra == 'langchain'
Requires-Dist: langchain-community>=0.4.1; extra == 'langchain'
Requires-Dist: langchain-core>=0.3.0; extra == 'langchain'
Requires-Dist: langchain-openai>=1.1.5; extra == 'langchain'
Requires-Dist: langgraph>=1.0.5; extra == 'langchain'
Provides-Extra: litellm
Requires-Dist: litellm>=1.70.0; extra == 'litellm'
Provides-Extra: opentelemetry
Requires-Dist: opentelemetry-api==1.38.0; extra == 'opentelemetry'
Requires-Dist: opentelemetry-exporter-otlp-proto-common==1.38.0; extra == 'opentelemetry'
Requires-Dist: opentelemetry-exporter-otlp-proto-grpc==1.38.0; extra == 'opentelemetry'
Requires-Dist: opentelemetry-exporter-otlp-proto-http==1.38.0; extra == 'opentelemetry'
Requires-Dist: opentelemetry-sdk==1.38.0; extra == 'opentelemetry'
Provides-Extra: strands
Requires-Dist: boto3>=1.34.0; extra == 'strands'
Requires-Dist: strands-agents-tools>=0.2.0; extra == 'strands'
Requires-Dist: strands-agents>=1.15.0; extra == 'strands'
